gchat_sdk/__init__.py
gchat_sdk/main.py
gchat_sdk/settings.py
gchat_sdk/utils.py
gchat_sdk/controllers/__init__.py
gchat_sdk/controllers/chat_controller.py
gchat_sdk/entities/__init__.py
gchat_sdk/entities/chat.py
gchat_sdk/factories/__init__.py
gchat_sdk/factories/chat_factory.py
gchat_sdk/providers/__init__.py
gchat_sdk/providers/chatbot_provider.py
gchat_sdk/tests/__init__.py
gchat_sdk/tests/constants.py
gchat_sdk/tests/test_chat.py
gchat_sdk/tests/test_chat_controller.py
gchat_sdk/tests/test_chat_factory.py
gchat_sdk/tests/test_error.py
gchat_sdk/tests/utils.py
gchat_sdk-0.1.2.dist-info/licenses/LICENSE
gchat_sdk-0.1.2.dist-info/METADATA
gchat_sdk-0.1.2.dist-info/WHEEL
gchat_sdk-0.1.2.dist-info/top_level.txt
gchat_sdk-0.1.2.dist-info/RECORD
