Metadata-Version: 2.4
Name: gchat-sdk
Version: 0.1.2
Summary: Gchat SDK for managing and closing conversations
Author: Tatianno Alves
Author-email: tferreiraalves@gmail.com
License: MIT License
Keywords: gchat chatbot sdk gnew
License-File: LICENSE
Dynamic: author
Dynamic: author-email
Dynamic: description
Dynamic: description-content-type
Dynamic: keywords
Dynamic: license
Dynamic: license-file
Dynamic: summary
